test_cases/__init__.py
test_cases/test_board.py
test_cases/test_game.py
test_cases/test_player.py
test_cases/test_snakeandladdder.py
test_cases/test_util.py
snakeandladder-0.1.0.dist-info/LICENSE.txt
snakeandladder-0.1.0.dist-info/METADATA
snakeandladder-0.1.0.dist-info/WHEEL
snakeandladder-0.1.0.dist-info/top_level.txt
snakeandladder-0.1.0.dist-info/RECORD
