Metadata-Version: 2.1
Name: snakeandladder
Version: 0.1.0
Summary: A Python implementation of the Snake and Ladder game
Home-page: https://github.com/mohbay95/Project_533
Author: Mohammed and Vidal
Author-email: Mohammed and Vidal <example@gmail.com>
Project-URL: Homepage, https://github.com/mohbay95/Project_533.git
Project-URL: Issues, https://github.com/mohbay95/Project_533.git/issues
Classifier: Programming Language :: Python :: 3
Classifier: License :: OSI Approved :: MIT License
Classifier: Operating System :: OS Independent
Requires-Python: >=3.6
License-File: LICENSE.txt
Requires-Dist: Art
